metacalls/__init__.py
metacalls/__version__.py
metacalls/binding.py
metacalls/environment.py
metacalls/exceptions.py
metacalls/ffprobe.py
metacalls/file_manager.py
metacalls/metacalls.py
metacalls/metacalls_session.py
metacalls/scaffold.py
metacalls/stream_type.py
metacalls/sync.py
metacalls/version_manager.py
metacalls/custom_api/__init__.py
metacalls/custom_api/custom_api.py
metacalls/dist/binding.js
metacalls/dist/buffer_optimized.js
metacalls/dist/ffmpeg_reader.js
metacalls/dist/file_reader.js
metacalls/dist/index.js
metacalls/dist/rtc-connection.js
metacalls/dist/sdp-builder.js
metacalls/dist/stream.js
metacalls/dist/tgcalls.js
metacalls/dist/types.js
metacalls/dist/utils.js
metacalls/handlers/__init__.py
metacalls/handlers/handlers_holder.py
metacalls/media_devices/__init__.py
metacalls/media_devices/device_info.py
metacalls/media_devices/media_devices.py
metacalls/media_devices/screen_info.py
metacalls/methods/__init__.py
metacalls/methods/core/__init__.py
metacalls/methods/core/binding_runner.py
metacalls/methods/core/join_voice_call.py
metacalls/methods/core/leave_voice_call.py
metacalls/methods/core/set_video_call_status.py
metacalls/methods/decorators/__init__.py
metacalls/methods/decorators/on_closed_voice_chat.py
metacalls/methods/decorators/on_group_call_invite.py
metacalls/methods/decorators/on_kicked.py
metacalls/methods/decorators/on_left.py
metacalls/methods/decorators/on_participants_change.py
metacalls/methods/decorators/on_raw_update.py
metacalls/methods/decorators/on_stream_end.py
metacalls/methods/groups/__init__.py
metacalls/methods/groups/active_calls.py
metacalls/methods/groups/calls.py
metacalls/methods/groups/change_volume_call.py
metacalls/methods/groups/get_active_call.py
metacalls/methods/groups/get_call.py
metacalls/methods/groups/get_participants.py
metacalls/methods/groups/join_group_call.py
metacalls/methods/groups/leave_group_call.py
metacalls/methods/handlers/__init__.py
metacalls/methods/handlers/raw_update_handler.py
MetaCalls-0.0.5.dist-info/LICENSE
MetaCalls-0.0.5.dist-info/METADATA
MetaCalls-0.0.5.dist-info/WHEEL
MetaCalls-0.0.5.dist-info/top_level.txt
MetaCalls-0.0.5.dist-info/RECORD
